README.md
setup.py
syncdir3.py
syncdir.egg-info/PKG-INFO
syncdir.egg-info/SOURCES.txt
syncdir.egg-info/dependency_links.txt
syncdir.egg-info/requires.txt
syncdir.egg-info/top_level.txt